[{"cui":"C0007144","definition":"Cardia of stomach"},{"cui":"C0015450","definition":"Body Regions"},{"cui":"C0016823","definition":"Structure of fundus of eye"},{"cui":"C0018670","definition":"Body Regions"},{"cui":"C0031066","definition":"Body Regions"},{"cui":"C0043262","definition":"Arm"},{"cui":"C0224519","definition":"Synchondrosis structure"},{"cui":"C0229089","definition":"Right eye"},{"cui":"C0230151","definition":"Costophrenic angle"},{"cui":"C0728992","definition":"Body Regions"},{"cui":"C0935456","definition":"Temple"},{"cui":"C1456858","definition":"Body Regions"}]